{
  "id": "708cc434-94dd-484e-b76c-b9c6eb1cbb35",
  "prevId": "423ba5a8-5a93-4dab-9dd5-57026a5bbd71",
  "version": "7",
  "dialect": "postgresql",
  "tables": {
    "public.client_receipt": {
      "name": "client_receipt",
      "schema": "",
      "columns": {
        "id": {
          "name": "id",
          "type": "text",
          "primaryKey": true,
          "notNull": true
        },
        "receipt_date": {
          "name": "receipt_date",
          "type": "timestamp with time zone",
          "primaryKey": false,
          "notNull": false
        },
        "competence": {
          "name": "competence",
          "type": "text",
          "primaryKey": false,
          "notNull": false
        },
        "cnpj": {
          "name": "cnpj",
          "type": "text",
          "primaryKey": false,
          "notNull": false
        },
        "client_name": {
          "name": "client_name",
          "type": "text",
          "primaryKey": false,
          "notNull": false
        },
        "percentage": {
          "name": "percentage",
          "type": "real",
          "primaryKey": false,
          "notNull": false
        },
        "compensation_month": {
          "name": "compensation_month",
          "type": "text",
          "primaryKey": false,
          "notNull": false
        },
        "honorary": {
          "name": "honorary",
          "type": "real",
          "primaryKey": false,
          "notNull": false
        },
        "tax": {
          "name": "tax",
          "type": "real",
          "primaryKey": false,
          "notNull": false
        },
        "status": {
          "name": "status",
          "type": "text",
          "primaryKey": false,
          "notNull": false
        },
        "created_at": {
          "name": "created_at",
          "type": "timestamp with time zone",
          "primaryKey": false,
          "notNull": true,
          "default": "now()"
        },
        "updated_at": {
          "name": "updated_at",
          "type": "timestamp with time zone",
          "primaryKey": false,
          "notNull": true,
          "default": "now()"
        }
      },
      "indexes": {},
      "foreignKeys": {},
      "compositePrimaryKeys": {},
      "uniqueConstraints": {},
      "policies": {},
      "checkConstraints": {},
      "isRLSEnabled": false
    },
    "public.clients": {
      "name": "clients",
      "schema": "",
      "columns": {
        "id": {
          "name": "id",
          "type": "text",
          "primaryKey": true,
          "notNull": true
        },
        "enterprise": {
          "name": "enterprise",
          "type": "text",
          "primaryKey": false,
          "notNull": false
        },
        "cnpj": {
          "name": "cnpj",
          "type": "text",
          "primaryKey": false,
          "notNull": false
        },
        "product": {
          "name": "product",
          "type": "text",
          "primaryKey": false,
          "notNull": false
        },
        "competence_month": {
          "name": "competence_month",
          "type": "text",
          "primaryKey": false,
          "notNull": false
        },
        "contestation": {
          "name": "contestation",
          "type": "text",
          "primaryKey": false,
          "notNull": false
        },
        "return": {
          "name": "return",
          "type": "text",
          "primaryKey": false,
          "notNull": false
        },
        "created_at": {
          "name": "created_at",
          "type": "timestamp with time zone",
          "primaryKey": false,
          "notNull": true,
          "default": "now()"
        },
        "updated_at": {
          "name": "updated_at",
          "type": "timestamp with time zone",
          "primaryKey": false,
          "notNull": true,
          "default": "now()"
        }
      },
      "indexes": {},
      "foreignKeys": {},
      "compositePrimaryKeys": {},
      "uniqueConstraints": {},
      "policies": {},
      "checkConstraints": {},
      "isRLSEnabled": false
    },
    "public.contracts": {
      "name": "contracts",
      "schema": "",
      "columns": {
        "id": {
          "name": "id",
          "type": "text",
          "primaryKey": true,
          "notNull": true
        },
        "city": {
          "name": "city",
          "type": "text",
          "primaryKey": false,
          "notNull": false
        },
        "clients": {
          "name": "clients",
          "type": "text",
          "primaryKey": false,
          "notNull": false
        },
        "state": {
          "name": "state",
          "type": "text",
          "primaryKey": false,
          "notNull": false
        },
        "cnpj": {
          "name": "cnpj",
          "type": "text",
          "primaryKey": false,
          "notNull": false
        },
        "sindic": {
          "name": "sindic",
          "type": "text",
          "primaryKey": false,
          "notNull": false
        },
        "year": {
          "name": "year",
          "type": "text",
          "primaryKey": false,
          "notNull": false
        },
        "matter": {
          "name": "matter",
          "type": "text",
          "primaryKey": false,
          "notNull": false
        },
        "forecast": {
          "name": "forecast",
          "type": "text",
          "primaryKey": false,
          "notNull": false
        },
        "contract_total": {
          "name": "contract_total",
          "type": "text",
          "primaryKey": false,
          "notNull": false
        },
        "percentage": {
          "name": "percentage",
          "type": "real",
          "primaryKey": false,
          "notNull": false
        },
        "signed_contract": {
          "name": "signed_contract",
          "type": "text",
          "primaryKey": false,
          "notNull": false
        },
        "status": {
          "name": "status",
          "type": "text",
          "primaryKey": false,
          "notNull": false
        },
        "average_guide": {
          "name": "average_guide",
          "type": "real",
          "primaryKey": false,
          "notNull": false
        },
        "partner": {
          "name": "partner",
          "type": "text",
          "primaryKey": false,
          "notNull": false
        },
        "partner_commission": {
          "name": "partner_commission",
          "type": "real",
          "primaryKey": false,
          "notNull": false
        },
        "counter": {
          "name": "counter",
          "type": "text",
          "primaryKey": false,
          "notNull": false
        },
        "email": {
          "name": "email",
          "type": "text",
          "primaryKey": false,
          "notNull": false
        },
        "created_at": {
          "name": "created_at",
          "type": "timestamp with time zone",
          "primaryKey": false,
          "notNull": true,
          "default": "now()"
        },
        "updated_at": {
          "name": "updated_at",
          "type": "timestamp with time zone",
          "primaryKey": false,
          "notNull": true,
          "default": "now()"
        }
      },
      "indexes": {},
      "foreignKeys": {},
      "compositePrimaryKeys": {},
      "uniqueConstraints": {},
      "policies": {},
      "checkConstraints": {},
      "isRLSEnabled": false
    },
    "public.credentials": {
      "name": "credentials",
      "schema": "",
      "columns": {
        "id": {
          "name": "id",
          "type": "text",
          "primaryKey": true,
          "notNull": true
        },
        "channel_head": {
          "name": "channel_head",
          "type": "text",
          "primaryKey": false,
          "notNull": false
        },
        "partner": {
          "name": "partner",
          "type": "text",
          "primaryKey": false,
          "notNull": false
        },
        "cnpj": {
          "name": "cnpj",
          "type": "text",
          "primaryKey": false,
          "notNull": false
        },
        "agent_indicator": {
          "name": "agent_indicator",
          "type": "text",
          "primaryKey": false,
          "notNull": false
        },
        "created_at": {
          "name": "created_at",
          "type": "timestamp with time zone",
          "primaryKey": false,
          "notNull": true,
          "default": "now()"
        },
        "updated_at": {
          "name": "updated_at",
          "type": "timestamp with time zone",
          "primaryKey": false,
          "notNull": true,
          "default": "now()"
        }
      },
      "indexes": {},
      "foreignKeys": {},
      "compositePrimaryKeys": {},
      "uniqueConstraints": {},
      "policies": {},
      "checkConstraints": {},
      "isRLSEnabled": false
    },
    "public.negotiation_imports": {
      "name": "negotiation_imports",
      "schema": "",
      "columns": {
        "id": {
          "name": "id",
          "type": "text",
          "primaryKey": true,
          "notNull": true
        },
        "title": {
          "name": "title",
          "type": "text",
          "primaryKey": false,
          "notNull": false
        },
        "client": {
          "name": "client",
          "type": "text",
          "primaryKey": false,
          "notNull": false
        },
        "user": {
          "name": "user",
          "type": "text",
          "primaryKey": false,
          "notNull": false
        },
        "tags": {
          "name": "tags",
          "type": "text",
          "primaryKey": false,
          "notNull": false
        },
        "step": {
          "name": "step",
          "type": "text",
          "primaryKey": false,
          "notNull": false
        },
        "status": {
          "name": "status",
          "type": "text",
          "primaryKey": false,
          "notNull": false
        },
        "value": {
          "name": "value",
          "type": "real",
          "primaryKey": false,
          "notNull": false
        },
        "starts_date": {
          "name": "starts_date",
          "type": "text",
          "primaryKey": false,
          "notNull": false
        },
        "observation": {
          "name": "observation",
          "type": "text",
          "primaryKey": false,
          "notNull": false
        },
        "partner_id": {
          "name": "partner_id",
          "type": "text",
          "primaryKey": false,
          "notNull": false
        },
        "average_guide": {
          "name": "average_guide",
          "type": "real",
          "primaryKey": false,
          "notNull": false
        },
        "created_at": {
          "name": "created_at",
          "type": "timestamp with time zone",
          "primaryKey": false,
          "notNull": true,
          "default": "now()"
        },
        "updated_at": {
          "name": "updated_at",
          "type": "timestamp with time zone",
          "primaryKey": false,
          "notNull": true,
          "default": "now()"
        }
      },
      "indexes": {},
      "foreignKeys": {},
      "compositePrimaryKeys": {},
      "uniqueConstraints": {},
      "policies": {},
      "checkConstraints": {},
      "isRLSEnabled": false
    },
    "public.partners": {
      "name": "partners",
      "schema": "",
      "columns": {
        "id": {
          "name": "id",
          "type": "text",
          "primaryKey": true,
          "notNull": true
        },
        "name": {
          "name": "name",
          "type": "text",
          "primaryKey": false,
          "notNull": false
        },
        "cpf_or_cnpj": {
          "name": "cpf_or_cnpj",
          "type": "text",
          "primaryKey": false,
          "notNull": false
        },
        "city": {
          "name": "city",
          "type": "text",
          "primaryKey": false,
          "notNull": false
        },
        "state": {
          "name": "state",
          "type": "text",
          "primaryKey": false,
          "notNull": false
        },
        "commission": {
          "name": "commission",
          "type": "real",
          "primaryKey": false,
          "notNull": false
        },
        "portal": {
          "name": "portal",
          "type": "text",
          "primaryKey": false,
          "notNull": false
        },
        "channel_head": {
          "name": "channel_head",
          "type": "text",
          "primaryKey": false,
          "notNull": false
        },
        "regional": {
          "name": "regional",
          "type": "text",
          "primaryKey": false,
          "notNull": false
        },
        "coordinator": {
          "name": "coordinator",
          "type": "text",
          "primaryKey": false,
          "notNull": false
        },
        "agent": {
          "name": "agent",
          "type": "text",
          "primaryKey": false,
          "notNull": false
        },
        "indicator": {
          "name": "indicator",
          "type": "text",
          "primaryKey": false,
          "notNull": false
        },
        "contract": {
          "name": "contract",
          "type": "text",
          "primaryKey": false,
          "notNull": false
        },
        "phone": {
          "name": "phone",
          "type": "text",
          "primaryKey": false,
          "notNull": false
        },
        "email": {
          "name": "email",
          "type": "text",
          "primaryKey": false,
          "notNull": false
        },
        "responsible": {
          "name": "responsible",
          "type": "text",
          "primaryKey": false,
          "notNull": false
        },
        "created_at": {
          "name": "created_at",
          "type": "timestamp with time zone",
          "primaryKey": false,
          "notNull": true,
          "default": "now()"
        },
        "updated_at": {
          "name": "updated_at",
          "type": "timestamp with time zone",
          "primaryKey": false,
          "notNull": true,
          "default": "now()"
        }
      },
      "indexes": {},
      "foreignKeys": {},
      "compositePrimaryKeys": {},
      "uniqueConstraints": {},
      "policies": {},
      "checkConstraints": {},
      "isRLSEnabled": false
    },
    "public.pending_issues": {
      "name": "pending_issues",
      "schema": "",
      "columns": {
        "id": {
          "name": "id",
          "type": "text",
          "primaryKey": true,
          "notNull": true
        },
        "client": {
          "name": "client",
          "type": "text",
          "primaryKey": false,
          "notNull": false
        },
        "call_reason": {
          "name": "call_reason",
          "type": "text",
          "primaryKey": false,
          "notNull": false
        },
        "status": {
          "name": "status",
          "type": "pending_status",
          "typeSchema": "public",
          "primaryKey": false,
          "notNull": false
        },
        "priority": {
          "name": "priority",
          "type": "text",
          "primaryKey": false,
          "notNull": false
        },
        "Responsible": {
          "name": "Responsible",
          "type": "text",
          "primaryKey": false,
          "notNull": false
        },
        "category": {
          "name": "category",
          "type": "pending_category",
          "typeSchema": "public",
          "primaryKey": false,
          "notNull": false
        },
        "description": {
          "name": "description",
          "type": "text",
          "primaryKey": false,
          "notNull": false
        },
        "created_at": {
          "name": "created_at",
          "type": "timestamp with time zone",
          "primaryKey": false,
          "notNull": true,
          "default": "now()"
        },
        "updated_at": {
          "name": "updated_at",
          "type": "timestamp with time zone",
          "primaryKey": false,
          "notNull": true,
          "default": "now()"
        }
      },
      "indexes": {},
      "foreignKeys": {},
      "compositePrimaryKeys": {},
      "uniqueConstraints": {},
      "policies": {},
      "checkConstraints": {},
      "isRLSEnabled": false
    },
    "public.portal_controls": {
      "name": "portal_controls",
      "schema": "",
      "columns": {
        "id": {
          "name": "id",
          "type": "text",
          "primaryKey": true,
          "notNull": true
        },
        "month_of_calculation": {
          "name": "month_of_calculation",
          "type": "text",
          "primaryKey": false,
          "notNull": false
        },
        "competence_month": {
          "name": "competence_month",
          "type": "text",
          "primaryKey": false,
          "notNull": false
        },
        "contract": {
          "name": "contract",
          "type": "real",
          "primaryKey": false,
          "notNull": false
        },
        "enterprise": {
          "name": "enterprise",
          "type": "text",
          "primaryKey": false,
          "notNull": false
        },
        "product": {
          "name": "product",
          "type": "text",
          "primaryKey": false,
          "notNull": false
        },
        "percentage_honorary": {
          "name": "percentage_honorary",
          "type": "real",
          "primaryKey": false,
          "notNull": false
        },
        "compensation": {
          "name": "compensation",
          "type": "real",
          "primaryKey": false,
          "notNull": false
        },
        "honorary": {
          "name": "honorary",
          "type": "real",
          "primaryKey": false,
          "notNull": false
        },
        "tax": {
          "name": "tax",
          "type": "real",
          "primaryKey": false,
          "notNull": false
        },
        "tj": {
          "name": "tj",
          "type": "real",
          "primaryKey": false,
          "notNull": false
        },
        "value": {
          "name": "value",
          "type": "real",
          "primaryKey": false,
          "notNull": false
        },
        "situation": {
          "name": "situation",
          "type": "text",
          "primaryKey": false,
          "notNull": false
        },
        "partner_id": {
          "name": "partner_id",
          "type": "text",
          "primaryKey": false,
          "notNull": true
        },
        "created_at": {
          "name": "created_at",
          "type": "timestamp with time zone",
          "primaryKey": false,
          "notNull": true,
          "default": "now()"
        },
        "updated_at": {
          "name": "updated_at",
          "type": "timestamp with time zone",
          "primaryKey": false,
          "notNull": true,
          "default": "now()"
        }
      },
      "indexes": {},
      "foreignKeys": {
        "portal_controls_partner_id_partners_id_fk": {
          "name": "portal_controls_partner_id_partners_id_fk",
          "tableFrom": "portal_controls",
          "tableTo": "partners",
          "columnsFrom": [
            "partner_id"
          ],
          "columnsTo": [
            "id"
          ],
          "onDelete": "no action",
          "onUpdate": "no action"
        }
      },
      "compositePrimaryKeys": {},
      "uniqueConstraints": {},
      "policies": {},
      "checkConstraints": {},
      "isRLSEnabled": false
    },
    "public.users": {
      "name": "users",
      "schema": "",
      "columns": {
        "id": {
          "name": "id",
          "type": "text",
          "primaryKey": true,
          "notNull": true
        },
        "email": {
          "name": "email",
          "type": "text",
          "primaryKey": false,
          "notNull": true
        },
        "password_hash": {
          "name": "password_hash",
          "type": "text",
          "primaryKey": false,
          "notNull": true
        },
        "role": {
          "name": "role",
          "type": "text",
          "primaryKey": false,
          "notNull": true
        },
        "created_at": {
          "name": "created_at",
          "type": "timestamp with time zone",
          "primaryKey": false,
          "notNull": true,
          "default": "now()"
        },
        "updated_at": {
          "name": "updated_at",
          "type": "timestamp with time zone",
          "primaryKey": false,
          "notNull": true,
          "default": "now()"
        }
      },
      "indexes": {},
      "foreignKeys": {},
      "compositePrimaryKeys": {},
      "uniqueConstraints": {
        "users_email_unique": {
          "name": "users_email_unique",
          "nullsNotDistinct": false,
          "columns": [
            "email"
          ]
        }
      },
      "policies": {},
      "checkConstraints": {},
      "isRLSEnabled": false
    }
  },
  "enums": {
    "public.pending_category": {
      "name": "pending_category",
      "schema": "public",
      "values": [
        "SAC",
        "Atendimento",
        "Financeiro",
        "Diretoria",
        "Comercial",
        "Auditoria"
      ]
    },
    "public.pending_status": {
      "name": "pending_status",
      "schema": "public",
      "values": [
        "Aberto",
        "Encaminhado",
        "Pendente",
        "Concluído"
      ]
    },
    "public.status": {
      "name": "status",
      "schema": "public",
      "values": [
        "Ativos",
        "Finalizados",
        "Em Andamento",
        "Em migração"
      ]
    }
  },
  "schemas": {},
  "sequences": {},
  "roles": {},
  "policies": {},
  "views": {},
  "_meta": {
    "columns": {},
    "schemas": {},
    "tables": {}
  }
}